{
  "frame": "0025_10",
  "predictions": [
    {
      "track_id": 0,
      "bbox": [
        278,
        168,
        302,
        240
      ],
      "speed": 10.0,
      "intent": "moving"
    },
    {
      "track_id": 1,
      "bbox": [
        408,
        168,
        432,
        240
      ],
      "speed": 6.0,
      "intent": "moving"
    },
    {
      "track_id": 2,
      "bbox": [
        668,
        88,
        692,
        160
      ],
      "speed": 0.0,
      "intent": "stationary"
    },
    {
      "track_id": 3,
      "bbox": [
        308,
        88,
        332,
        160
      ],
      "speed": 12.0,
      "intent": "moving"
    }
  ]
}